wavelogpostmanager/__init__.py
wavelogpostmanager/__main__.py
wavelogpostmanager/boostrap.py
wavelogpostmanager/client_contacts.py
wavelogpostmanager/client_queue.py
wavelogpostmanager/connection_test_entrypoint.py
wavelogpostmanager/docx_generate_test_entrypoint.py
wavelogpostmanager/entrypoint.py
wavelogpostmanager/local_contacts.py
wavelogpostmanager/local_queue.py
wavelogpostmanager/queue_and_contacts_entrypoint.py
wavelogpostmanager/signoff_list_entrypoint.py
wavelogpostmanager/client/__init__.py
wavelogpostmanager/client/client.py
wavelogpostmanager/config/__init__.py
wavelogpostmanager/config/config_context.py
wavelogpostmanager/config/mysql_context.py
wavelogpostmanager/constants/__init__.py
wavelogpostmanager/constants/core_constant.py
wavelogpostmanager/constants/default_config.py
wavelogpostmanager/constants/languages.py
wavelogpostmanager/constants/langs/__init__.py
wavelogpostmanager/constants/langs/en.py
wavelogpostmanager/constants/langs/zh_cn.py
wavelogpostmanager/database/__init__.py
wavelogpostmanager/database/common_dao.py
wavelogpostmanager/database/contacts_dao.py
wavelogpostmanager/database/contacts_processor.py
wavelogpostmanager/database/data_processor.py
wavelogpostmanager/database/mysql_dao.py
wavelogpostmanager/database/rcvd_dao.py
wavelogpostmanager/database/signoff_dao.py
wavelogpostmanager/database/signoff_processor.py
wavelogpostmanager/docx_generator/__init__.py
wavelogpostmanager/docx_generator/docx_generator.py
wavelogpostmanager/exceptions/__init__.py
wavelogpostmanager/listener/__init__.py
wavelogpostmanager/listener/listener.py
wavelogpostmanager/mailbot/__init__.py
wavelogpostmanager/mailbot/mailbot.py
wavelogpostmanager/server/__init__.py
wavelogpostmanager/server/server.py
wavelogpostmanager/server/server_runner.py
wavelogpostmanager/utils/__init__.py
wavelogpostmanager/utils/client_load_contact_by_toml.py
wavelogpostmanager/utils/create_toml.py
wavelogpostmanager/utils/generate_example_contacts_toml.py
wavelogpostmanager-0.0.1b2.dist-info/LICENSE
wavelogpostmanager-0.0.1b2.dist-info/METADATA
wavelogpostmanager-0.0.1b2.dist-info/WHEEL
wavelogpostmanager-0.0.1b2.dist-info/entry_points.txt
wavelogpostmanager-0.0.1b2.dist-info/top_level.txt
wavelogpostmanager-0.0.1b2.dist-info/RECORD
